singler-0.5.0.dist-info/RECORD
singler-0.5.0.dist-info/WHEEL
singler-0.5.0.dist-info/top_level.txt
singler-0.5.0.dist-info/METADATA
singler-0.5.0.dist-info/licenses/LICENSE.txt
singler/_train_integrated.py
singler/_mock_data.py
singler/_annotate_single.py
singler/__init__.py
singler/_get_classic_markers.py
singler/_lib_singler.cpython-314-darwin.so
singler/_train_single.py
singler/_annotate_integrated.py
singler/_aggregate_reference.py
singler/_classify_integrated.py
singler/_classify_single.py
singler/_utils.py
