Metadata-Version: 2.4
Name: singler
Version: 0.5.0
Summary: Python bindings to the singleR algorithm to annotate cell types from known references.
Home-page: https://github.com/BiocPy/singler
Author: Aaron Lun
Author-email: lun.aaron@gene.com
License: MIT
Project-URL: Documentation, https://github.com/BiocPy/singler
Platform: any
Classifier: Development Status :: 4 - Beta
Classifier: Programming Language :: Python
Requires-Python: >=3.9
License-File: LICENSE.txt
Requires-Dist: importlib-metadata; python_version < "3.8"
Requires-Dist: mattress>=0.4.0
Requires-Dist: knncolle>=0.2.0
Requires-Dist: delayedarray
Requires-Dist: biocframe>=0.6.0
Requires-Dist: summarizedexperiment>=0.6.0
Requires-Dist: singlecellexperiment>=0.6.0
Requires-Dist: biocutils>=0.2.0
Provides-Extra: optional
Requires-Dist: celldex; extra == "optional"
Requires-Dist: scranpy>=0.3.0; extra == "optional"
Requires-Dist: scipy; extra == "optional"
Requires-Dist: scrnaseq; extra == "optional"
Provides-Extra: testing
Requires-Dist: setuptools; extra == "testing"
Requires-Dist: pytest; extra == "testing"
Requires-Dist: pytest-cov; extra == "testing"
Requires-Dist: celldex; extra == "testing"
Requires-Dist: scranpy>=0.3.0; extra == "testing"
Requires-Dist: scipy; extra == "testing"
Requires-Dist: scrnaseq; extra == "testing"
Dynamic: license-file
